{"house_id": 5747, "goals": {"1": ["SoapBottle", "DiningTable"], "2": ["Ladle", "DiningTable"], "3": ["Pencil", "ShelvingUnit"], "4": ["Fork", "CounterTop"], "5": ["Bottle", "CounterTop"], "6": ["Bread", "CounterTop"], "7": ["Ladle", "CounterTop"], "8": ["Pencil", "CounterTop"], "9": ["Fork", "DiningTable"], "10": ["Ladle", "DiningTable"], "11": ["SprayBottle", "GarbageCan"], "12": ["Bottle", "ShelvingUnit"], "13": ["Mug", "ShelvingUnit"], "14": ["SoapBottle", "CounterTop"], "15": ["Bread", "GarbageCan"], "16": ["SoapBottle", "ShelvingUnit"], "17": ["Ladle", "CounterTop"], "18": ["Vase", "ShelvingUnit"], "19": ["Fork", "CounterTop"], "20": ["Ladle", "DiningTable"]}, "spawn_objects": [{"objectName": "Bottle|surface|2|4", "position": {"x": 1.5, "y": 0.0, "z": 4.5}, "rotation": {"x": -0.01, "y": 0.0, "z": 0.0}}, {"objectName": "Bread|surface|2|12", "position": {"x": 2.5, "y": 0.0, "z": 5.5}, "rotation": {"x": -0.0, "y": 0.0, "z": -0.0}}], "start_pose": [1.25, 0.9, 3.25], "initial_orientation": 90.0}