{"house_id": 5829, "goals": {"1": ["Knife", "Sink"], "2": ["Mug", "CounterTop"], "3": ["Statue", "CounterTop"], "4": ["Potato", "DiningTable"], "5": ["DishSponge", "GarbageCan"], "6": ["RemoteControl", "DiningTable"], "7": ["Knife", "DiningTable"], "8": ["Book", "DiningTable"], "9": ["Fork", "Mug"], "10": ["DishSponge", "Sink"], "11": ["ButterKnife", "Mug"], "12": ["Fork", "Sink"], "13": ["Statue", "DiningTable"], "14": ["Book", "Sofa"], "15": ["Potato", "Sink"], "16": ["Book", "CounterTop"], "17": ["DishSponge", "CounterTop"], "18": ["Fork", "Mug"], "19": ["ButterKnife", "Sink"], "20": ["Potato", "DiningTable"]}, "spawn_objects": [{"objectName": "Apple|surface|8|14", "position": {"x": 11.25, "y": 0.0, "z": 7.5}, "rotation": {"x": -0.0, "y": 0.0, "z": 0.0}}, {"objectName": "Book|surface|6|3", "position": {"x": 12.0, "y": 0.0, "z": 7.25}, "rotation": {"x": -0.0, "y": 90.0, "z": 0.01}}, {"objectName": "Book|surface|6|4", "position": {"x": 14.5, "y": 0.0, "z": 4.0}, "rotation": {"x": 0.02, "y": 90.0, "z": 0.91}}, {"objectName": "ButterKnife|surface|8|16", "position": {"x": 12.0, "y": 0.0, "z": 6.0}, "rotation": {"x": 0.02, "y": 270.0, "z": 1.42}}, {"objectName": "CreditCard|surface|4|0", "position": {"x": 6.0, "y": 0.0, "z": 8.5}, "rotation": {"x": 0.0, "y": 90.0, "z": -0.0}}, {"objectName": "DishSponge|surface|7|11", "position": {"x": 3.75, "y": 0.0, "z": 7.75}, "rotation": {"x": 0.08, "y": 359.99, "z": 0.03}}, {"objectName": "Egg|surface|8|19", "position": {"x": 8.75, "y": 0.0, "z": 3.25}, "rotation": {"x": -0.0, "y": 0.0, "z": 0.0}}, {"objectName": "Fork|surface|8|15", "position": {"x": 6.5, "y": 0.0, "z": 8.5}, "rotation": {"x": 0.35, "y": 270.0, "z": 359.82}}, {"objectName": "Knife|surface|8|12", "position": {"x": 12.0, "y": 0.0, "z": 9.0}, "rotation": {"x": 353.9, "y": 269.63, "z": 5.12}}, {"objectName": "Lettuce|surface|8|18", "position": {"x": 2.75, "y": 0.0, "z": 7.25}, "rotation": {"x": 0.02, "y": 90.0, "z": 2.61}}, {"objectName": "Mug|surface|6|8", "position": {"x": 9.25, "y": 0.0, "z": 8.5}, "rotation": {"x": -0.0, "y": -0.0, "z": -0.0}}, {"objectName": "Mug|surface|4|1", "position": {"x": 14.75, "y": 0.0, "z": 2.75}, "rotation": {"x": 0.0, "y": 90.0, "z": -0.0}}, {"objectName": "Pillow|6|1|1", "position": {"x": 12.25, "y": 0.0, "z": 5.25}, "rotation": {"x": 0.0, "y": 180.0, "z": 0.0}}, {"objectName": "Pillow|4|0|2", "position": {"x": 9.75, "y": 0.0, "z": 6.75}, "rotation": {"x": -0.0, "y": 90.0, "z": 0.0}}, {"objectName": "Pillow|surface|9|23", "position": {"x": 10.75, "y": 0.0, "z": 7.75}, "rotation": {"x": 0.0, "y": 180.0, "z": -0.0}}, {"objectName": "Pillow|4|0|1", "position": {"x": 10.0, "y": 0.0, "z": 7.0}, "rotation": {"x": -0.0, "y": 90.0, "z": 0.0}}, {"objectName": "Potato|surface|8|17", "position": {"x": 3.0, "y": 0.0, "z": 7.5}, "rotation": {"x": 0.28, "y": 269.67, "z": 5.43}}, {"objectName": "RemoteControl|surface|9|21", "position": {"x": 16.0, "y": 0.0, "z": 7.0}, "rotation": {"x": 0.0, "y": 180.0, "z": -0.0}}, {"objectName": "Statue|surface|6|6", "position": {"x": 14.75, "y": 0.0, "z": 3.5}, "rotation": {"x": -0.0, "y": -0.0, "z": 0.0}}], "start_pose": [8.75, 0.9, 4.0], "initial_orientation": 180.0}