{"house_id": 9010, "goals": {"1": ["Pen", "GarbageCan"], "2": ["Vase", "DiningTable"], "3": ["WineBottle", "ShelvingUnit"], "4": ["Book", "ShelvingUnit"], "5": ["AlarmClock", "DiningTable"], "6": ["SprayBottle", "GarbageCan"], "7": ["Bowl", "ShelvingUnit"], "8": ["Mug", "CounterTop"], "9": ["Pen", "ShelvingUnit"], "10": ["AlarmClock", "ShelvingUnit"], "11": ["Mug", "ShelvingUnit"], "12": ["Spoon", "Plate"], "13": ["Newspaper", "ArmChair"], "14": ["CreditCard", "ShelvingUnit"], "15": ["Pillow", "ArmChair"], "16": ["Vase", "ShelvingUnit"], "17": ["Apple", "Pot"], "18": ["Statue", "DiningTable"], "19": ["Spoon", "CounterTop"], "20": ["Knife", "Pan"]}, "spawn_objects": [{"objectName": "AlarmClock|surface|2|30", "position": {"x": 1.0, "y": 0.0, "z": 1.75}, "rotation": {"x": 0.0, "y": 90.0, "z": 0.0}}, {"objectName": "Apple|surface|6|11", "position": {"x": 5.0, "y": 0.0, "z": 3.75}, "rotation": {"x": 0.0, "y": 0.0, "z": 0.0}}, {"objectName": "Book|surface|2|24", "position": {"x": 9.25, "y": 0.0, "z": 3.25}, "rotation": {"x": 0.01, "y": 90.0, "z": 0.3}}, {"objectName": "Book|surface|2|25", "position": {"x": 6.5, "y": 0.0, "z": 5.5}, "rotation": {"x": -0.0, "y": 90.0, "z": 0.07}}, {"objectName": "Book|surface|2|26", "position": {"x": 9.25, "y": 0.0, "z": 3.75}, "rotation": {"x": 0.0, "y": 90.0, "z": 359.98}}, {"objectName": "Bowl|surface|6|9", "position": {"x": 8.0, "y": 0.0, "z": 3.0}, "rotation": {"x": 0.0, "y": 180.0, "z": -0.0}}, {"objectName": "Bowl|surface|2|29", "position": {"x": 3.75, "y": 0.0, "z": 5.25}, "rotation": {"x": -0.0, "y": 90.0, "z": -0.0}}, {"objectName": "CreditCard|surface|2|23", "position": {"x": 3.5, "y": 0.0, "z": 3.25}, "rotation": {"x": 0.0, "y": -0.0, "z": -0.0}}, {"objectName": "Fork|surface|6|7", "position": {"x": 5.5, "y": 0.0, "z": 5.5}, "rotation": {"x": 0.36, "y": 150.0, "z": 0.52}}], "start_pose": [2.0, 0.9, 1.5], "initial_orientation": 180.0}