{"house_id": 9243, "goals": {"1": ["Statue", "CounterTop"], "2": ["WineBottle", "GarbageCan"], "3": ["CellPhone", "Sofa"], "4": ["Watch", "DiningTable"], "5": ["Pan", "DiningTable"], "6": ["CellPhone", "ShelvingUnit"], "7": ["RemoteControl", "ShelvingUnit"], "8": ["Bowl", "Sink"], "9": ["Book", "ShelvingUnit"], "10": ["Pencil", "GarbageCan"], "11": ["Apple", "GarbageCan"], "12": ["Vase", "ShelvingUnit"], "13": ["TissueBox", "ShelvingUnit"], "14": ["Fork", "DiningTable"], "15": ["Book", "DiningTable"], "16": ["AlarmClock", "CounterTop"], "17": ["Bowl", "ShelvingUnit"], "18": ["TissueBox", "GarbageCan"], "19": ["Book", "DiningTable"], "20": ["Watch", "ShelvingUnit"]}, "spawn_objects": [{"objectName": "AlarmClock|surface|10|91", "position": {"x": 6.75, "y": 0.0, "z": 2.5}, "rotation": {"x": 0.0, "y": 180.0, "z": 0.0}}], "start_pose": [3.75, 0.9, 8.0], "initial_orientation": 90.0}