{"house_id": 9264, "goals": {"1": ["SoapBottle", "DiningTable"], "2": ["Mug", "DiningTable"], "3": ["Knife", "Plate"], "4": ["Bottle", "DiningTable"], "5": ["Spoon", "Plate"], "6": ["Fork", "Mug"], "7": ["RemoteControl", "CounterTop"], "8": ["Knife", "Mug"], "9": ["Spoon", "Mug"], "10": ["SoapBottle", "CounterTop"], "11": ["Newspaper", "CounterTop"], "12": ["SprayBottle", "DiningTable"], "13": ["Apple", "Plate"], "14": ["DishSponge", "Plate"], "15": ["SoapBottle", "DiningTable"], "16": ["ButterKnife", "Mug"], "17": ["Fork", "Plate"], "18": ["Bottle", "CounterTop"], "19": ["Newspaper", "DiningTable"], "20": ["Spoon", "Plate"]}, "spawn_objects": [{"objectName": "Apple|surface|2|0", "position": {"x": 4.25, "y": 0.0, "z": 5.5}, "rotation": {"x": 0.0, "y": 270.0, "z": 0.0}}, {"objectName": "Bottle|surface|2|1", "position": {"x": 1.75, "y": 0.0, "z": 4.0}, "rotation": {"x": 359.99, "y": 0.0, "z": 0.0}}, {"objectName": "ButterKnife|surface|2|4", "position": {"x": 1.25, "y": 0.0, "z": 2.0}, "rotation": {"x": 0.0, "y": 0.0, "z": 0.08}}, {"objectName": "DishSponge|surface|2|13", "position": {"x": 1.0, "y": 0.0, "z": 6.75}, "rotation": {"x": 0.0, "y": 90.0, "z": -0.0}}, {"objectName": "Fork|surface|2|7", "position": {"x": 2.25, "y": 0.0, "z": 6.75}, "rotation": {"x": 0.35, "y": 270.0, "z": 359.82}}, {"objectName": "Knife|surface|2|8", "position": {"x": 1.75, "y": 0.0, "z": 4.5}, "rotation": {"x": 353.31, "y": 89.87, "z": 2.96}}, {"objectName": "Mug|surface|2|9", "position": {"x": 0.75, "y": 0.0, "z": 6.25}, "rotation": {"x": 0.0, "y": -0.0, "z": -0.0}}, {"objectName": "Newspaper|surface|3|17", "position": {"x": 5.0, "y": 0.0, "z": 6.5}, "rotation": {"x": 359.44, "y": 270.01, "z": 359.94}}, {"objectName": "Pencil|surface|3|18", "position": {"x": 1.5, "y": 0.0, "z": 2.25}, "rotation": {"x": 359.91, "y": 270.0, "z": 0.03}}], "start_pose": [6.0, 0.9, 5.75], "initial_orientation": 0.0}