{"house_id": 4591, "goals": {"1": ["Watch", "ShelvingUnit"], "2": ["RemoteControl", "Sofa"], "3": ["CD", "CounterTop"], "4": ["Pen", "CounterTop"], "5": ["Bowl", "Sink"], "6": ["Ladle", "Pot"], "7": ["Mug", "DiningTable"], "8": ["SoapBottle", "ShelvingUnit"], "9": ["RemoteControl", "ArmChair"], "10": ["AlarmClock", "CounterTop"], "11": ["RemoteControl", "ArmChair"], "12": ["Pen", "DiningTable"], "13": ["Statue", "CounterTop"], "14": ["Book", "ShelvingUnit"], "15": ["Cup", "Sink"], "16": ["Ladle", "Sink"], "17": ["Bread", "GarbageCan"], "18": ["Newspaper", "DiningTable"], "19": ["Lettuce", "Sink"], "20": ["Ladle", "Pot"]}, "spawn_objects": [{"objectName": "AlarmClock|surface|4|0", "position": {"x": 2.75, "y": 0.0, "z": 7.75}, "rotation": {"x": 0.0, "y": 0.0, "z": -0.0}}, {"objectName": "Apple|surface|6|16", "position": {"x": 4.0, "y": 0.0, "z": 4.75}, "rotation": {"x": -0.0, "y": 90.0, "z": -0.0}}, {"objectName": "Book|surface|4|7", "position": {"x": 3.5, "y": 0.0, "z": 2.75}, "rotation": {"x": 0.03, "y": 90.0, "z": 0.32}}, {"objectName": "Bottle|surface|6|21", "position": {"x": 7.25, "y": 0.0, "z": 4.5}, "rotation": {"x": 359.99, "y": 0.0, "z": 0.0}}, {"objectName": "Bowl|surface|6|22", "position": {"x": 4.0, "y": 0.0, "z": 5.25}, "rotation": {"x": 0.18, "y": 0.0, "z": 0.0}}, {"objectName": "Bowl|surface|7|40", "position": {"x": 6.5, "y": 0.0, "z": 5.0}, "rotation": {"x": 0.0, "y": 0.0, "z": -0.0}}, {"objectName": "Bread|surface|6|31", "position": {"x": 2.0, "y": 0.0, "z": 2.5}, "rotation": {"x": -0.0, "y": 90.0, "z": -0.0}}, {"objectName": "Candle|surface|7|46", "position": {"x": 7.25, "y": 0.0, "z": 5.0}, "rotation": {"x": 0.0, "y": 270.0, "z": -0.0}}, {"objectName": "CD|surface|4|3", "position": {"x": 4.0, "y": 0.0, "z": 6.0}, "rotation": {"x": -0.0, "y": -0.0, "z": 0.0}}, {"objectName": "Cup|surface|6|17", "position": {"x": 8.0, "y": 0.0, "z": 4.0}, "rotation": {"x": -0.01, "y": -0.0, "z": 359.99}}], "start_pose": [7.0, 0.9, 7.0], "initial_orientation": 0.0}