{"house_id": 9848, "goals": {"1": ["Book", "Sofa"], "2": ["Newspaper", "Bed"], "3": ["Spatula", "Bowl"], "4": ["Pencil", "GarbageCan"], "5": ["Newspaper", "GarbageCan"], "6": ["Book", "DiningTable"], "7": ["AlarmClock", "DiningTable"], "8": ["Book", "ArmChair"], "9": ["CellPhone", "DiningTable"], "10": ["Egg", "GarbageCan"], "11": ["Newspaper", "DiningTable"], "12": ["RemoteControl", "ArmChair"], "13": ["Book", "Bed"], "14": ["Spatula", "DiningTable"], "15": ["RemoteControl", "DiningTable"], "16": ["Newspaper", "GarbageCan"], "17": ["Egg", "Plate"], "18": ["Knife", "DiningTable"], "19": ["ButterKnife", "Bowl"], "20": ["SoapBottle", "GarbageCan"]}, "spawn_objects": [{"objectName": "AlarmClock|surface|2|29", "position": {"x": 2.25, "y": 0.0, "z": 5.5}, "rotation": {"x": 359.77, "y": 180.0, "z": 0.0}}, {"objectName": "Book|surface|7|24", "position": {"x": 4.5, "y": 0.0, "z": 1.5}, "rotation": {"x": -0.0, "y": 90.0, "z": 0.09}}], "start_pose": [6.5, 0.9, 3.75], "initial_orientation": 90.0}