{"house_id": 9068, "goals": {"1": ["RemoteControl", "CounterTop"], "2": ["Pencil", "Mug"], "3": ["CellPhone", "Sofa"], "4": ["Mug", "CounterTop"], "5": ["SprayBottle", "GarbageCan"], "6": ["Mug", "DiningTable"], "7": ["TissueBox", "GarbageCan"], "8": ["CD", "DiningTable"], "9": ["Mug", "CounterTop"], "10": ["CellPhone", "CounterTop"], "11": ["RemoteControl", "Sofa"], "12": ["Vase", "DiningTable"], "13": ["Pencil", "DiningTable"], "14": ["CreditCard", "Sofa"], "15": ["Mug", "DiningTable"], "16": ["CreditCard", "DiningTable"], "17": ["Statue", "Cart"], "18": ["Vase", "Cart"], "19": ["Statue", "DiningTable"], "20": ["Pencil", "GarbageCan"]}, "spawn_objects": [{"objectName": "Book|surface|7|14", "position": {"x": 3.75, "y": 0.0, "z": 1.75}, "rotation": {"x": 0.0, "y": -0.0, "z": 0.26}}], "start_pose": [3.0, 0.9, 3.25], "initial_orientation": 0.0}