{"house_id": 194, "goals": {"1": ["WineBottle", "ShelvingUnit"], "2": ["SoapBottle", "ShelvingUnit"], "3": ["Egg", "DiningTable"], "4": ["Pencil", "ShelvingUnit"], "5": ["CellPhone", "CounterTop"], "6": ["Mug", "DiningTable"], "7": ["RemoteControl", "CounterTop"], "8": ["Mug", "ShelvingUnit"], "9": ["Statue", "Cart"], "10": ["Potato", "CounterTop"], "11": ["Egg", "CounterTop"], "12": ["CreditCard", "ShelvingUnit"], "13": ["SprayBottle", "ShelvingUnit"], "14": ["CellPhone", "DiningTable"], "15": ["Potato", "Bowl"], "16": ["Bowl", "CounterTop"], "17": ["Candle", "CounterTop"], "18": ["Statue", "ShelvingUnit"], "19": ["CellPhone", "CounterTop"], "20": ["Pencil", "DiningTable"]}, "spawn_objects": [{"objectName": "Book|surface|2|29", "position": {"x": 5.5, "y": 0.0, "z": 6.5}, "rotation": {"x": -0.0, "y": 0.0, "z": 0.2}}, {"objectName": "Book|surface|7|21", "position": {"x": 1.5, "y": 0.0, "z": 3.0}, "rotation": {"x": 359.99, "y": 90.0, "z": 0.11}}, {"objectName": "Book|surface|2|30", "position": {"x": 6.75, "y": 0.0, "z": 7.5}, "rotation": {"x": 0.0, "y": 270.0, "z": 0.0}}, {"objectName": "Book|surface|6|10", "position": {"x": 5.5, "y": 0.0, "z": 7.75}, "rotation": {"x": 359.99, "y": 0.0, "z": 0.03}}, {"objectName": "Bowl|surface|7|27", "position": {"x": 4.75, "y": 0.0, "z": 7.0}, "rotation": {"x": 359.99, "y": -0.0, "z": 359.84}}, {"objectName": "Bowl|surface|2|32", "position": {"x": 6.75, "y": 0.0, "z": 9.0}, "rotation": {"x": 0.0, "y": 90.0, "z": -0.0}}, {"objectName": "Bowl|surface|6|7", "position": {"x": 4.5, "y": 0.0, "z": 7.75}, "rotation": {"x": -0.0, "y": 90.0, "z": -0.0}}, {"objectName": "Candle|surface|7|19", "position": {"x": 6.0, "y": 0.0, "z": 7.5}, "rotation": {"x": 0.03, "y": 359.99, "z": 359.98}}, {"objectName": "CellPhone|surface|6|14", "position": {"x": 7.75, "y": 0.0, "z": 7.25}, "rotation": {"x": 0.0, "y": 90.0, "z": -0.0}}, {"objectName": "CreditCard|surface|7|20", "position": {"x": 4.25, "y": 0.0, "z": 3.0}, "rotation": {"x": 0.0, "y": 0.0, "z": -0.0}}, {"objectName": "Egg|surface|6|9", "position": {"x": 2.5, "y": 0.0, "z": 2.0}, "rotation": {"x": -0.0, "y": 0.0, "z": 0.0}}, {"objectName": "Egg|surface|6|11", "position": {"x": 3.0, "y": 0.0, "z": 6.25}, "rotation": {"x": 0.0, "y": 180.0, "z": 0.0}}, {"objectName": "Lettuce|surface|6|5", "position": {"x": 6.0, "y": 0.0, "z": 7.25}, "rotation": {"x": 13.33, "y": 359.92, "z": 359.48}}], "start_pose": [8.75, 0.9, 7.25], "initial_orientation": 90.0}