{"house_id": 558, "goals": {"1": ["Pencil", "ShelvingUnit"], "2": ["Egg", "DiningTable"], "3": ["Spoon", "Pot"], "4": ["Pen", "GarbageCan"], "5": ["Spoon", "DiningTable"], "6": ["Pen", "ShelvingUnit"], "7": ["Spoon", "Bowl"], "8": ["Pencil", "GarbageCan"], "9": ["Cup", "ShelvingUnit"], "10": ["TissueBox", "ShelvingUnit"], "11": ["Pen", "DiningTable"], "12": ["WineBottle", "ShelvingUnit"], "13": ["Spoon", "Pot"], "14": ["Potato", "Plate"], "15": ["CellPhone", "CounterTop"], "16": ["RemoteControl", "ArmChair"], "17": ["TissueBox", "DiningTable"], "18": ["Potato", "Bowl"], "19": ["RemoteControl", "CounterTop"], "20": ["Tomato", "Pot"]}, "spawn_objects": [{"objectName": "Apple|surface|2|14", "position": {"x": 2.75, "y": 0.0, "z": 7.0}, "rotation": {"x": -0.0, "y": 0.0, "z": 0.0}}, {"objectName": "Book|surface|2|23", "position": {"x": 6.0, "y": 0.0, "z": 2.75}, "rotation": {"x": -0.0, "y": 0.0, "z": 0.2}}, {"objectName": "Book|surface|2|13", "position": {"x": 3.5, "y": 0.0, "z": 7.0}, "rotation": {"x": 0.06, "y": 90.0, "z": 0.14}}, {"objectName": "Bowl|surface|3|30", "position": {"x": 5.0, "y": 0.0, "z": 7.5}, "rotation": {"x": 0.0, "y": 225.0, "z": 0.0}}, {"objectName": "Bread|surface|2|3", "position": {"x": 2.0, "y": 0.0, "z": 5.25}, "rotation": {"x": -0.0, "y": 0.0, "z": -0.0}}, {"objectName": "Bread|surface|2|18", "position": {"x": 3.75, "y": 0.0, "z": 6.75}, "rotation": {"x": 0.0, "y": 270.0, "z": 0.0}}, {"objectName": "CellPhone|surface|2|19", "position": {"x": 4.0, "y": 0.0, "z": 1.5}, "rotation": {"x": 0.0, "y": 270.0, "z": -0.0}}, {"objectName": "CreditCard|surface|3|31", "position": {"x": 5.25, "y": 0.0, "z": 1.25}, "rotation": {"x": -0.0, "y": 90.0, "z": -0.0}}], "start_pose": [5.5, 0.9, 5.0], "initial_orientation": 0.0}