{"house_id": 1037, "goals": {"1": ["DishSponge", "ShelvingUnit"], "2": ["Mug", "ShelvingUnit"], "3": ["RemoteControl", "Box"], "4": ["Bowl", "ShelvingUnit"], "5": ["Statue", "CounterTop"], "6": ["CellPhone", "CounterTop"], "7": ["Candle", "DiningTable"], "8": ["CellPhone", "Sofa"], "9": ["DishSponge", "Pot"], "10": ["Candle", "Box"], "11": ["Pencil", "Mug"], "12": ["DishSponge", "DiningTable"], "13": ["ButterKnife", "Bowl"], "14": ["Candle", "ShelvingUnit"], "15": ["ButterKnife", "CounterTop"], "16": ["Watch", "DiningTable"], "17": ["RemoteControl", "ShelvingUnit"], "18": ["Pen", "ShelvingUnit"], "19": ["Book", "Sofa"], "20": ["RemoteControl", "DiningTable"]}, "spawn_objects": [{"objectName": "Apple|surface|2|11", "position": {"x": 2.75, "y": 0.0, "z": 4.75}, "rotation": {"x": -0.0, "y": 0.0, "z": 0.0}}, {"objectName": "Book|surface|2|1", "position": {"x": 3.75, "y": 0.0, "z": 1.5}, "rotation": {"x": 0.02, "y": 180.0, "z": 0.09}}, {"objectName": "Book|surface|3|25", "position": {"x": 2.75, "y": 0.0, "z": 5.5}, "rotation": {"x": 359.99, "y": 180.0, "z": 0.07}}, {"objectName": "Book|surface|3|38", "position": {"x": 2.75, "y": 0.0, "z": 4.0}, "rotation": {"x": 0.0, "y": 0.0, "z": 359.98}}], "start_pose": [2.75, 0.9, 7.75], "initial_orientation": 90.0}