{"house_id": 2308, "goals": {"1": ["Pillow", "ArmChair"], "2": ["Egg", "Sink"], "3": ["SoapBottle", "Cart"], "4": ["CreditCard", "Sofa"], "5": ["RemoteControl", "CounterTop"], "6": ["Statue", "Cart"], "7": ["WineBottle", "GarbageCan"], "8": ["Vase", "Cart"], "9": ["Statue", "CounterTop"], "10": ["CellPhone", "DiningTable"], "11": ["Statue", "DiningTable"], "12": ["Mug", "DiningTable"], "13": ["Pillow", "Sofa"], "14": ["SprayBottle", "GarbageCan"], "15": ["RemoteControl", "ArmChair"], "16": ["Vase", "DiningTable"], "17": ["Apple", "GarbageCan"], "18": ["RemoteControl", "DiningTable"], "19": ["Vase", "CounterTop"], "20": ["Statue", "CounterTop"]}, "spawn_objects": [{"objectName": "AlarmClock|surface|4|5", "position": {"x": 6.5, "y": 0.0, "z": 1.0}, "rotation": {"x": 0.0, "y": 180.0, "z": 0.0}}, {"objectName": "Apple|surface|8|24", "position": {"x": 7.0, "y": 0.0, "z": 4.75}, "rotation": {"x": -0.0, "y": 0.0, "z": 0.0}}, {"objectName": "Book|surface|9|41", "position": {"x": 6.0, "y": 0.0, "z": 1.5}, "rotation": {"x": 0.01, "y": 180.0, "z": 0.3}}, {"objectName": "Book|surface|4|7", "position": {"x": 4.0, "y": 0.0, "z": 8.25}, "rotation": {"x": 0.0, "y": 0.0, "z": 359.98}}, {"objectName": "Book|surface|8|32", "position": {"x": 9.25, "y": 0.0, "z": 6.25}, "rotation": {"x": -0.0, "y": 0.0, "z": 0.2}}, {"objectName": "Book|surface|6|21", "position": {"x": 6.75, "y": 0.0, "z": 5.25}, "rotation": {"x": 359.99, "y": 270.0, "z": 0.09}}, {"objectName": "Bowl|surface|6|19", "position": {"x": 9.25, "y": 0.0, "z": 6.75}, "rotation": {"x": 359.99, "y": 270.0, "z": 0.25}}, {"objectName": "ButterKnife|surface|8|29", "position": {"x": 3.25, "y": 0.0, "z": 5.25}, "rotation": {"x": 0.02, "y": 90.0, "z": 1.28}}, {"objectName": "Candle|surface|5|15", "position": {"x": 1.5, "y": 0.0, "z": 7.25}, "rotation": {"x": 0.01, "y": 179.98, "z": 359.96}}, {"objectName": "CellPhone|surface|4|11", "position": {"x": 6.75, "y": 0.0, "z": 5.0}, "rotation": {"x": 0.0, "y": 270.0, "z": -0.0}}], "start_pose": [4.75, 0.9, 1.75], "initial_orientation": 0.0}