{"house_id": 3464, "goals": {"1": ["WineBottle", "DiningTable"], "2": ["Fork", "Mug"], "3": ["Bread", "GarbageCan"], "4": ["Bowl", "DiningTable"], "5": ["ButterKnife", "Sink"], "6": ["Pencil", "DiningTable"], "7": ["ButterKnife", "DiningTable"], "8": ["AlarmClock", "DiningTable"], "9": ["Cup", "DiningTable"], "10": ["Fork", "Bowl"], "11": ["Pen", "GarbageCan"], "12": ["Bowl", "CounterTop"], "13": ["Bread", "DiningTable"], "14": ["ButterKnife", "DiningTable"], "15": ["Ladle", "CounterTop"], "16": ["Fork", "Bowl"], "17": ["WineBottle", "SideTable"], "18": ["Newspaper", "Bed"], "19": ["Mug", "CounterTop"], "20": ["Pencil", "GarbageCan"]}, "spawn_objects": [{"objectName": "AlarmClock|surface|4|13", "position": {"x": 5.0, "y": 0.0, "z": 1.75}, "rotation": {"x": -0.0, "y": -0.0, "z": 0.0}}, {"objectName": "Book|surface|7|43", "position": {"x": 6.75, "y": 0.0, "z": 2.0}, "rotation": {"x": -0.0, "y": 135.0, "z": 0.03}}, {"objectName": "Bowl|surface|4|2", "position": {"x": 3.75, "y": 0.0, "z": 3.25}, "rotation": {"x": -0.0, "y": 0.0, "z": 0.0}}, {"objectName": "Bowl|surface|7|41", "position": {"x": 8.0, "y": 0.0, "z": 5.25}, "rotation": {"x": 0.0, "y": 180.0, "z": 0.0}}, {"objectName": "Bread|surface|6|36", "position": {"x": 3.5, "y": 0.0, "z": 5.75}, "rotation": {"x": 0.0, "y": 270.0, "z": -0.0}}, {"objectName": "Bread|surface|6|35", "position": {"x": 6.25, "y": 0.0, "z": 1.25}, "rotation": {"x": -0.0, "y": 270.0, "z": -0.0}}, {"objectName": "ButterKnife|surface|6|31", "position": {"x": 3.75, "y": 0.0, "z": 7.0}, "rotation": {"x": 0.0, "y": 270.0, "z": 0.08}}, {"objectName": "ButterKnife|surface|6|25", "position": {"x": 8.25, "y": 0.0, "z": 6.75}, "rotation": {"x": 0.0, "y": 0.0, "z": 0.07}}, {"objectName": "CellPhone|surface|4|12", "position": {"x": 9.25, "y": 0.0, "z": 2.25}, "rotation": {"x": 0.0, "y": 180.0, "z": -0.0}}, {"objectName": "CellPhone|surface|6|39", "position": {"x": 3.75, "y": 0.0, "z": 6.5}, "rotation": {"x": -0.0, "y": 180.0, "z": -0.0}}, {"objectName": "CellPhone|surface|4|4", "position": {"x": 8.25, "y": 0.0, "z": 7.25}, "rotation": {"x": -0.0, "y": 90.0, "z": -0.0}}], "start_pose": [1.75, 0.9, 4.5], "initial_orientation": 0.0}