{"house_id": 4453, "goals": {"1": ["Knife", "Sink"], "2": ["RemoteControl", "DiningTable"], "3": ["CreditCard", "ShelvingUnit"], "4": ["Watch", "CounterTop"], "5": ["Cup", "ShelvingUnit"], "6": ["Book", "ShelvingUnit"], "7": ["Mug", "DiningTable"], "8": ["Watch", "ShelvingUnit"], "9": ["Bowl", "DiningTable"], "10": ["Watch", "ShelvingUnit"], "11": ["Knife", "CounterTop"], "12": ["Mug", "ShelvingUnit"], "13": ["Book", "CounterTop"], "14": ["Bowl", "ShelvingUnit"], "15": ["Knife", "Pan"], "16": ["SoapBottle", "ShelvingUnit"], "17": ["Mug", "DiningTable"], "18": ["TissueBox", "DiningTable"], "19": ["Mug", "CounterTop"], "20": ["CellPhone", "CounterTop"]}, "spawn_objects": [{"objectName": "AlarmClock|surface|4|3", "position": {"x": 8.75, "y": 0.0, "z": 6.75}, "rotation": {"x": -0.0, "y": 270.0, "z": 0.0}}, {"objectName": "Book|surface|6|33", "position": {"x": 6.0, "y": 0.0, "z": 3.25}, "rotation": {"x": 0.0, "y": 192.79, "z": 0.0}}, {"objectName": "Book|surface|6|34", "position": {"x": 8.0, "y": 0.0, "z": 5.75}, "rotation": {"x": -0.0, "y": -0.0, "z": 0.09}}, {"objectName": "Book|surface|4|16", "position": {"x": 7.25, "y": 0.0, "z": 4.25}, "rotation": {"x": -0.0, "y": 270.0, "z": 0.09}}, {"objectName": "Book|surface|4|0", "position": {"x": 7.5, "y": 0.0, "z": 8.5}, "rotation": {"x": 0.06, "y": 270.0, "z": 0.14}}, {"objectName": "Bowl|surface|6|40", "position": {"x": 7.5, "y": 0.0, "z": 5.0}, "rotation": {"x": 0.0, "y": 0.0, "z": 0.25}}, {"objectName": "Bowl|surface|4|9", "position": {"x": 7.0, "y": 0.0, "z": 8.0}, "rotation": {"x": -0.0, "y": 270.0, "z": 0.0}}, {"objectName": "Bread|surface|6|24", "position": {"x": 8.25, "y": 0.0, "z": 6.25}, "rotation": {"x": -0.0, "y": 270.0, "z": -0.0}}, {"objectName": "CellPhone|surface|4|14", "position": {"x": 7.75, "y": 0.0, "z": 4.0}, "rotation": {"x": 0.0, "y": 270.0, "z": -0.0}}, {"objectName": "CellPhone|surface|7|50", "position": {"x": 11.0, "y": 0.0, "z": 6.0}, "rotation": {"x": 0.0, "y": 90.0, "z": -0.0}}, {"objectName": "CreditCard|surface|6|35", "position": {"x": 10.5, "y": 0.0, "z": 10.75}, "rotation": {"x": 0.0, "y": 270.0, "z": -0.0}}, {"objectName": "CreditCard|surface|7|45", "position": {"x": 9.0, "y": 0.0, "z": 8.25}, "rotation": {"x": 0.0, "y": 0.0, "z": -0.0}}, {"objectName": "Cup|surface|6|30", "position": {"x": 10.0, "y": 0.0, "z": 4.0}, "rotation": {"x": 0.03, "y": 0.0, "z": 0.02}}, {"objectName": "Cup|surface|6|29", "position": {"x": 9.75, "y": 0.0, "z": 3.0}, "rotation": {"x": -0.0, "y": -0.0, "z": -0.0}}, {"objectName": "Egg|surface|6|38", "position": {"x": 7.25, "y": 0.0, "z": 5.5}, "rotation": {"x": 359.07, "y": 89.94, "z": 6.69}}, {"objectName": "Egg|surface|6|37", "position": {"x": 7.75, "y": 0.0, "z": 8.5}, "rotation": {"x": 0.0, "y": 90.0, "z": 0.0}}], "start_pose": [3.5, 0.9, 3.0], "initial_orientation": 270.0}