{"house_id": 4468, "goals": {"1": ["CreditCard", "CounterTop"], "2": ["Pencil", "GarbageCan"], "3": ["Newspaper", "CounterTop"], "4": ["Potato", "GarbageCan"], "5": ["Bread", "DiningTable"], "6": ["SoapBottle", "DiningTable"], "7": ["Candle", "CounterTop"], "8": ["Bread", "CounterTop"], "9": ["Statue", "CounterTop"], "10": ["Ladle", "Bowl"], "11": ["Newspaper", "GarbageCan"], "12": ["Pan", "DiningTable"], "13": ["Newspaper", "DiningTable"], "14": ["Pan", "CounterTop"], "15": ["Egg", "GarbageCan"], "16": ["Apple", "DiningTable"], "17": ["SoapBottle", "CounterTop"], "18": ["Spoon", "Bowl"], "19": ["CreditCard", "DiningTable"], "20": ["Spatula", "Pan"]}, "spawn_objects": [{"objectName": "Apple|surface|2|10", "position": {"x": 1.5, "y": 0.0, "z": 3.0}, "rotation": {"x": 0.0, "y": -0.0, "z": 359.99}}, {"objectName": "Bottle|surface|2|9", "position": {"x": 1.0, "y": 0.0, "z": 3.5}, "rotation": {"x": 359.98, "y": 0.0, "z": 0.0}}, {"objectName": "Bowl|surface|3|20", "position": {"x": 0.75, "y": 0.0, "z": 3.25}, "rotation": {"x": 0.0, "y": 0.0, "z": -0.0}}, {"objectName": "Bowl|surface|2|18", "position": {"x": 2.25, "y": 0.0, "z": 3.25}, "rotation": {"x": -0.0, "y": -0.0, "z": -0.0}}, {"objectName": "Bread|surface|2|12", "position": {"x": 1.5, "y": 0.0, "z": 3.25}, "rotation": {"x": -0.0, "y": 90.0, "z": -0.0}}, {"objectName": "Candle|surface|3|23", "position": {"x": 2.0, "y": 0.0, "z": 3.0}, "rotation": {"x": 0.03, "y": 359.99, "z": 359.98}}, {"objectName": "CellPhone|surface|2|7", "position": {"x": 1.25, "y": 0.0, "z": 2.75}, "rotation": {"x": 0.0, "y": 0.0, "z": -0.0}}, {"objectName": "CreditCard|surface|3|24", "position": {"x": 2.5, "y": 0.0, "z": 3.5}, "rotation": {"x": 0.0, "y": 0.0, "z": -0.0}}, {"objectName": "Egg|surface|2|4", "position": {"x": 2.5, "y": 0.0, "z": 3.25}, "rotation": {"x": 0.0, "y": 180.0, "z": 0.0}}, {"objectName": "Egg|surface|2|5", "position": {"x": 1.0, "y": 0.0, "z": 3.0}, "rotation": {"x": 0.0, "y": 180.0, "z": 0.0}}, {"objectName": "Egg|surface|2|3", "position": {"x": 2.25, "y": 0.0, "z": 3.75}, "rotation": {"x": -0.0, "y": 0.0, "z": 0.0}}, {"objectName": "Egg|surface|2|6", "position": {"x": 0.75, "y": 0.0, "z": 3.75}, "rotation": {"x": 0.0, "y": 180.0, "z": 0.0}}], "start_pose": [3.25, 0.9, 3.25], "initial_orientation": 0.0}