{"house_id": 5655, "goals": {"1": ["Fork", "Mug"], "2": ["SprayBottle", "CounterTop"], "3": ["Fork", "Pan"], "4": ["SoapBottle", "DiningTable"], "5": ["Mug", "ShelvingUnit"], "6": ["Knife", "Pan"], "7": ["Apple", "Pot"], "8": ["Ladle", "Plate"], "9": ["Knife", "CounterTop"], "10": ["CellPhone", "ShelvingUnit"], "11": ["Pencil", "ShelvingUnit"], "12": ["Apple", "CounterTop"], "13": ["Spoon", "Pan"], "14": ["SprayBottle", "ShelvingUnit"], "15": ["Ladle", "CounterTop"], "16": ["Spoon", "CounterTop"], "17": ["Statue", "DiningTable"], "18": ["Fork", "Plate"], "19": ["Statue", "ShelvingUnit"], "20": ["Fork", "Pot"]}, "spawn_objects": [{"objectName": "Apple|surface|2|10", "position": {"x": 2.0, "y": 0.0, "z": 3.0}, "rotation": {"x": 0.0, "y": 180.0, "z": 0.0}}], "start_pose": [1.25, 0.9, 5.5], "initial_orientation": 180.0}