{"house_id": 4761, "goals": {"1": ["RemoteControl", "CounterTop"], "2": ["Tomato", "DiningTable"], "3": ["Potato", "DiningTable"], "4": ["SprayBottle", "DiningTable"], "5": ["Vase", "CounterTop"], "6": ["Knife", "DiningTable"], "7": ["Tomato", "CounterTop"], "8": ["SoapBottle", "DiningTable"], "9": ["Lettuce", "CounterTop"], "10": ["Candle", "CounterTop"], "11": ["Vase", "CounterTop"], "12": ["DishSponge", "Plate"], "13": ["Knife", "DiningTable"], "14": ["Bowl", "CounterTop"], "15": ["Mug", "DiningTable"], "16": ["Vase", "DiningTable"], "17": ["Lettuce", "CounterTop"], "18": ["Mug", "CounterTop"], "19": ["Candle", "DiningTable"], "20": ["Bowl", "CounterTop"]}, "spawn_objects": [{"objectName": "AlarmClock|surface|2|21", "position": {"x": 2.0, "y": 0.0, "z": 5.25}, "rotation": {"x": -0.0, "y": 270.0, "z": 0.0}}, {"objectName": "Bowl|surface|7|14", "position": {"x": 2.0, "y": 0.0, "z": 2.75}, "rotation": {"x": 0.0, "y": 180.0, "z": 0.0}}, {"objectName": "Candle|surface|7|19", "position": {"x": 2.0, "y": 0.0, "z": 3.75}, "rotation": {"x": 0.0, "y": 180.0, "z": 359.99}}, {"objectName": "DishSponge|surface|6|5", "position": {"x": 5.25, "y": 0.0, "z": 1.25}, "rotation": {"x": 0.0, "y": 270.0, "z": -0.0}}, {"objectName": "Knife|surface|6|3", "position": {"x": 5.0, "y": 0.0, "z": 5.5}, "rotation": {"x": 353.79, "y": 269.84, "z": 2.91}}, {"objectName": "Lettuce|surface|6|0", "position": {"x": 3.75, "y": 0.0, "z": 5.5}, "rotation": {"x": 2.71, "y": 270.01, "z": 0.48}}, {"objectName": "Mug|surface|6|1", "position": {"x": 4.5, "y": 0.0, "z": 5.5}, "rotation": {"x": 0.0, "y": 270.0, "z": 0.0}}, {"objectName": "Potato|surface|6|11", "position": {"x": 6.5, "y": 0.0, "z": 1.25}, "rotation": {"x": 0.0, "y": 270.0, "z": -0.0}}, {"objectName": "Potato|surface|6|10", "position": {"x": 3.75, "y": 0.0, "z": 2.25}, "rotation": {"x": 3.9, "y": 270.0, "z": -0.0}}], "start_pose": [1.5, 0.9, 6.25], "initial_orientation": 180.0}