{"house_id": 6087, "goals": {"1": ["Pan", "DiningTable"], "2": ["SoapBottle", "DiningTable"], "3": ["Pan", "CounterTop"], "4": ["Book", "DiningTable"], "5": ["TissueBox", "DiningTable"], "6": ["Egg", "GarbageCan"], "7": ["Book", "Bed"], "8": ["SprayBottle", "DiningTable"], "9": ["CellPhone", "Sofa"], "10": ["Statue", "CounterTop"], "11": ["Book", "ArmChair"], "12": ["Pan", "CounterTop"], "13": ["Pillow", "Sofa"], "14": ["Egg", "DiningTable"], "15": ["TissueBox", "GarbageCan"], "16": ["Pan", "DiningTable"], "17": ["Bowl", "DiningTable"], "18": ["SprayBottle", "GarbageCan"], "19": ["TissueBox", "DiningTable"], "20": ["Fork", "Sink"]}, "spawn_objects": [{"objectName": "Apple|surface|2|4", "position": {"x": 6.75, "y": 0.0, "z": 1.25}, "rotation": {"x": 0.0, "y": 90.0, "z": 0.08}}, {"objectName": "Book|surface|6|25", "position": {"x": 10.0, "y": 0.0, "z": 8.5}, "rotation": {"x": -0.0, "y": 270.0, "z": 0.09}}, {"objectName": "Book|surface|2|1", "position": {"x": 7.0, "y": 0.0, "z": 4.5}, "rotation": {"x": 0.02, "y": 270.0, "z": 0.01}}, {"objectName": "Bowl|surface|4|16", "position": {"x": 10.0, "y": 0.0, "z": 9.0}, "rotation": {"x": 359.99, "y": 270.0, "z": 0.04}}, {"objectName": "CellPhone|surface|5|22", "position": {"x": 8.5, "y": 0.0, "z": 4.0}, "rotation": {"x": 0.0, "y": 180.0, "z": -0.0}}, {"objectName": "Cup|surface|2|0", "position": {"x": 9.0, "y": 0.0, "z": 5.25}, "rotation": {"x": 0.01, "y": 270.01, "z": 0.04}}, {"objectName": "DishSponge|surface|3|11", "position": {"x": 7.25, "y": 0.0, "z": 4.0}, "rotation": {"x": 359.98, "y": 90.0, "z": 359.95}}, {"objectName": "Egg|surface|2|9", "position": {"x": 8.25, "y": 0.0, "z": 5.25}, "rotation": {"x": 0.0, "y": 270.0, "z": 0.0}}, {"objectName": "Egg|surface|2|8", "position": {"x": 2.25, "y": 0.0, "z": 3.25}, "rotation": {"x": -0.0, "y": 270.0, "z": -0.0}}, {"objectName": "Fork|surface|2|6", "position": {"x": 4.25, "y": 0.0, "z": 6.0}, "rotation": {"x": 0.35, "y": 270.0, "z": 359.83}}, {"objectName": "Mug|surface|5|21", "position": {"x": 2.0, "y": 0.0, "z": 4.0}, "rotation": {"x": 0.0, "y": 90.0, "z": 0.0}}, {"objectName": "Pan|surface|2|5", "position": {"x": 1.25, "y": 0.0, "z": 6.25}, "rotation": {"x": 359.97, "y": 270.0, "z": 359.99}}, {"objectName": "Pillow|5|0|2", "position": {"x": 6.75, "y": 0.0, "z": 3.0}, "rotation": {"x": 0.0, "y": 180.0, "z": 0.0}}, {"objectName": "Pillow|5|0|1", "position": {"x": 9.75, "y": 0.0, "z": 5.25}, "rotation": {"x": 0.0, "y": 180.0, "z": 0.0}}, {"objectName": "Pillow|6|3|1", "position": {"x": 5.0, "y": 0.0, "z": 9.75}, "rotation": {"x": -0.0, "y": 180.0, "z": -0.0}}, {"objectName": "SoapBottle|surface|2|2", "position": {"x": 2.5, "y": 0.0, "z": 9.75}, "rotation": {"x": -0.0, "y": 270.0, "z": 0.0}}, {"objectName": "SprayBottle|surface|3|10", "position": {"x": 6.75, "y": 0.0, "z": 3.25}, "rotation": {"x": 359.96, "y": 90.0, "z": 359.78}}, {"objectName": "SprayBottle|surface|2|7", "position": {"x": 2.0, "y": 0.0, "z": 2.0}, "rotation": {"x": 0.01, "y": 270.0, "z": 0.04}}, {"objectName": "Statue|surface|6|27", "position": {"x": 3.5, "y": 0.0, "z": 6.5}, "rotation": {"x": 0.0, "y": 270.0, "z": 0.0}}], "start_pose": [7.5, 0.9, 3.25], "initial_orientation": 270.0}