{"house_id": 7104, "goals": {"1": ["Mug", "Sink"], "2": ["Tomato", "Plate"], "3": ["SprayBottle", "DiningTable"], "4": ["AlarmClock", "DiningTable"], "5": ["Mug", "DiningTable"], "6": ["CreditCard", "ShelvingUnit"], "7": ["RemoteControl", "ShelvingUnit"], "8": ["Vase", "CounterTop"], "9": ["CreditCard", "DiningTable"], "10": ["Fork", "Mug"], "11": ["Pencil", "ShelvingUnit"], "12": ["Mug", "Sink"], "13": ["TissueBox", "DiningTable"], "14": ["SoapBottle", "DiningTable"], "15": ["AlarmClock", "ShelvingUnit"], "16": ["Bowl", "Sink"], "17": ["Mug", "DiningTable"], "18": ["SprayBottle", "GarbageCan"], "19": ["AlarmClock", "DiningTable"], "20": ["Bowl", "ShelvingUnit"]}, "spawn_objects": [{"objectName": "AlarmClock|surface|4|9", "position": {"x": 7.5, "y": 0.0, "z": 4.5}, "rotation": {"x": -0.0, "y": -0.0, "z": -0.0}}, {"objectName": "Book|surface|4|12", "position": {"x": 12.5, "y": 0.0, "z": 4.75}, "rotation": {"x": -0.0, "y": 0.0, "z": 0.01}}, {"objectName": "Book|surface|6|26", "position": {"x": 2.0, "y": 0.0, "z": 5.25}, "rotation": {"x": 0.0, "y": 180.0, "z": 359.98}}, {"objectName": "Book|surface|7|38", "position": {"x": 2.0, "y": 0.0, "z": 6.75}, "rotation": {"x": 0.0, "y": 90.0, "z": 359.98}}, {"objectName": "Book|surface|4|7", "position": {"x": 7.5, "y": 0.0, "z": 7.0}, "rotation": {"x": -0.0, "y": 89.95, "z": 359.93}}, {"objectName": "Book|surface|4|6", "position": {"x": 11.75, "y": 0.0, "z": 8.75}, "rotation": {"x": 0.0, "y": 90.0, "z": 0.0}}, {"objectName": "Bowl|surface|7|35", "position": {"x": 4.75, "y": 0.0, "z": 11.5}, "rotation": {"x": 0.0, "y": 270.0, "z": -0.0}}, {"objectName": "Bowl|surface|4|11", "position": {"x": 7.75, "y": 0.0, "z": 6.5}, "rotation": {"x": -0.0, "y": 90.0, "z": 0.0}}, {"objectName": "CellPhone|surface|6|20", "position": {"x": 9.5, "y": 0.0, "z": 9.25}, "rotation": {"x": -0.0, "y": 180.0, "z": -0.0}}, {"objectName": "CellPhone|surface|7|36", "position": {"x": 6.0, "y": 0.0, "z": 6.25}, "rotation": {"x": 0.0, "y": 90.0, "z": -0.0}}, {"objectName": "CreditCard|surface|4|2", "position": {"x": 6.25, "y": 0.0, "z": 4.75}, "rotation": {"x": 0.0, "y": 90.0, "z": -0.0}}, {"objectName": "DishSponge|surface|6|29", "position": {"x": 7.75, "y": 0.0, "z": 4.0}, "rotation": {"x": -0.0, "y": 180.0, "z": -0.0}}, {"objectName": "Fork|surface|6|24", "position": {"x": 10.5, "y": 0.0, "z": 9.0}, "rotation": {"x": 0.0, "y": 180.0, "z": 0.0}}, {"objectName": "Mug|surface|4|4", "position": {"x": 7.0, "y": 0.0, "z": 5.0}, "rotation": {"x": 0.0, "y": 270.0, "z": -0.0}}, {"objectName": "Mug|surface|6|27", "position": {"x": 5.75, "y": 0.0, "z": 4.5}, "rotation": {"x": 0.0, "y": 180.0, "z": -0.0}}], "start_pose": [4.25, 0.9, 8.5], "initial_orientation": 0.0}