{"house_id": 7208, "goals": {"1": ["CreditCard", "ArmChair"], "2": ["Pillow", "Sofa"], "3": ["Mug", "CounterTop"], "4": ["Pen", "CounterTop"], "5": ["CellPhone", "ArmChair"], "6": ["Knife", "Pot"], "7": ["Statue", "DiningTable"], "8": ["Spatula", "DiningTable"], "9": ["Book", "CounterTop"], "10": ["Statue", "CounterTop"], "11": ["Book", "DiningTable"], "12": ["CreditCard", "CounterTop"], "13": ["Spatula", "Bowl"], "14": ["Knife", "Bowl"], "15": ["Mug", "DiningTable"], "16": ["Candle", "DiningTable"], "17": ["Statue", "DiningTable"], "18": ["CreditCard", "ArmChair"], "19": ["Pillow", "ArmChair"], "20": ["Bottle", "DiningTable"]}, "spawn_objects": [], "start_pose": [4.75, 0.9, 7.75], "initial_orientation": 0.0}