{"house_id": 7611, "goals": {"1": ["Book", "CounterTop"], "2": ["Candle", "CounterTop"], "3": ["ButterKnife", "Bowl"], "4": ["Statue", "DiningTable"], "5": ["Fork", "Bowl"], "6": ["Pencil", "DiningTable"], "7": ["Knife", "Bowl"], "8": ["Mug", "CounterTop"], "9": ["Pan", "CounterTop"], "10": ["Bowl", "CounterTop"], "11": ["Pencil", "CounterTop"], "12": ["Mug", "DiningTable"], "13": ["Tomato", "DiningTable"], "14": ["Mug", "CounterTop"], "15": ["SoapBottle", "DiningTable"], "16": ["Pan", "CounterTop"], "17": ["Mug", "Sink"], "18": ["Pen", "CounterTop"], "19": ["Pan", "DiningTable"], "20": ["Book", "ArmChair"]}, "spawn_objects": [{"objectName": "Book|surface|7|30", "position": {"x": 8.75, "y": 0.0, "z": 6.75}, "rotation": {"x": -0.0, "y": -0.0, "z": 0.01}}, {"objectName": "Book|surface|7|29", "position": {"x": 2.0, "y": 0.0, "z": 6.25}, "rotation": {"x": -0.0, "y": -0.0, "z": 0.09}}, {"objectName": "Book|surface|4|6", "position": {"x": 3.5, "y": 0.0, "z": 12.0}, "rotation": {"x": -0.0, "y": 90.0, "z": 0.85}}, {"objectName": "Bowl|surface|6|13", "position": {"x": 7.75, "y": 0.0, "z": 5.5}, "rotation": {"x": -0.0, "y": 180.0, "z": 0.0}}, {"objectName": "Bowl|surface|4|4", "position": {"x": 9.5, "y": 0.0, "z": 7.25}, "rotation": {"x": 0.0, "y": 90.0, "z": -0.0}}, {"objectName": "Bowl|surface|7|31", "position": {"x": 2.5, "y": 0.0, "z": 8.5}, "rotation": {"x": -0.0, "y": -0.0, "z": 0.0}}, {"objectName": "ButterKnife|surface|6|11", "position": {"x": 7.25, "y": 0.0, "z": 3.75}, "rotation": {"x": 0.02, "y": -0.0, "z": 1.51}}, {"objectName": "Candle|surface|7|28", "position": {"x": 3.25, "y": 0.0, "z": 6.0}, "rotation": {"x": 0.0, "y": -0.0, "z": -0.0}}, {"objectName": "Candle|surface|5|8", "position": {"x": 8.5, "y": 0.0, "z": 9.5}, "rotation": {"x": 0.13, "y": 180.1, "z": 355.08}}, {"objectName": "CD|surface|4|3", "position": {"x": 12.0, "y": 0.0, "z": 7.5}, "rotation": {"x": 0.0, "y": -0.0, "z": 0.0}}, {"objectName": "Fork|surface|6|14", "position": {"x": 7.0, "y": 0.0, "z": 6.75}, "rotation": {"x": 0.35, "y": 180.0, "z": 359.82}}, {"objectName": "Knife|surface|6|23", "position": {"x": 9.25, "y": 0.0, "z": 5.0}, "rotation": {"x": 353.72, "y": 89.8, "z": 3.36}}, {"objectName": "Mug|surface|4|0", "position": {"x": 9.75, "y": 0.0, "z": 5.5}, "rotation": {"x": 0.0, "y": 90.0, "z": -0.0}}, {"objectName": "Pan|surface|6|20", "position": {"x": 5.0, "y": 0.0, "z": 6.5}, "rotation": {"x": 0.1, "y": 180.0, "z": 0.04}}], "start_pose": [2.0, 0.9, 12.75], "initial_orientation": 180.0}