{"house_id": 7739, "goals": {"1": ["SprayBottle", "DiningTable"], "2": ["CellPhone", "ShelvingUnit"], "3": ["RemoteControl", "CounterTop"], "4": ["Mug", "Sink"], "5": ["CreditCard", "ShelvingUnit"], "6": ["Spoon", "Mug"], "7": ["Pencil", "ShelvingUnit"], "8": ["Knife", "Sink"], "9": ["Vase", "DiningTable"], "10": ["Knife", "Pot"], "11": ["Pillow", "Sofa"], "12": ["CellPhone", "ArmChair"], "13": ["AlarmClock", "CounterTop"], "14": ["Mug", "DiningTable"], "15": ["Pen", "Mug"], "16": ["CellPhone", "DiningTable"], "17": ["AlarmClock", "CounterTop"], "18": ["CreditCard", "DiningTable"], "19": ["AlarmClock", "CounterTop"], "20": ["SprayBottle", "CounterTop"]}, "spawn_objects": [], "start_pose": [2.75, 0.9, 7.5], "initial_orientation": 0.0}