{"house_id": 4955, "goals": {"1": ["Bowl", "ShelvingUnit"], "2": ["Book", "Sofa"], "3": ["RemoteControl", "ShelvingUnit"], "4": ["Mug", "ShelvingUnit"], "5": ["RemoteControl", "CounterTop"], "6": ["Vase", "DiningTable"], "7": ["Book", "DiningTable"], "8": ["Pen", "DiningTable"], "9": ["Fork", "DiningTable"], "10": ["Apple", "Plate"], "11": ["Egg", "DiningTable"], "12": ["Pen", "DiningTable"], "13": ["CreditCard", "CounterTop"], "14": ["Book", "Bed"], "15": ["Mug", "DiningTable"], "16": ["Bowl", "CounterTop"], "17": ["Apple", "CounterTop"], "18": ["Bowl", "DiningTable"], "19": ["Egg", "Pot"], "20": ["Potato", "Bowl"]}, "spawn_objects": [{"objectName": "Apple|surface|6|2", "position": {"x": 7.5, "y": 0.0, "z": 3.25}, "rotation": {"x": 0.0, "y": 90.0, "z": 0.0}}, {"objectName": "Book|surface|7|20", "position": {"x": 4.0, "y": 0.0, "z": 2.25}, "rotation": {"x": 359.93, "y": 180.0, "z": 0.03}}, {"objectName": "Book|surface|7|19", "position": {"x": 7.25, "y": 0.0, "z": 3.0}, "rotation": {"x": 0.01, "y": 0.0, "z": 0.78}}, {"objectName": "Bowl|surface|2|27", "position": {"x": 2.25, "y": 0.0, "z": 4.0}, "rotation": {"x": -0.0, "y": 270.0, "z": 0.0}}, {"objectName": "Bowl|surface|7|16", "position": {"x": 4.5, "y": 0.0, "z": 2.0}, "rotation": {"x": 359.99, "y": 180.0, "z": 0.04}}, {"objectName": "CreditCard|surface|7|18", "position": {"x": 2.75, "y": 0.0, "z": 2.5}, "rotation": {"x": 0.0, "y": 0.0, "z": -0.0}}, {"objectName": "CreditCard|surface|2|30", "position": {"x": 3.75, "y": 0.0, "z": 2.0}, "rotation": {"x": 0.0, "y": 270.0, "z": -0.0}}, {"objectName": "Egg|surface|6|10", "position": {"x": 5.75, "y": 0.0, "z": 1.25}, "rotation": {"x": 359.74, "y": 269.98, "z": 10.79}}], "start_pose": [1.75, 0.9, 3.0], "initial_orientation": 0.0}