{"house_id": 8098, "goals": {"1": ["Pillow", "Ottoman"], "2": ["Book", "DiningTable"], "3": ["Bowl", "DiningTable"], "4": ["CellPhone", "ShelvingUnit"], "5": ["Mug", "DiningTable"], "6": ["AlarmClock", "ShelvingUnit"], "7": ["CellPhone", "Bed"], "8": ["Vase", "DiningTable"], "9": ["RemoteControl", "Sofa"], "10": ["SprayBottle", "DiningTable"], "11": ["Pen", "ShelvingUnit"], "12": ["CellPhone", "DiningTable"], "13": ["Lettuce", "GarbageCan"], "14": ["Cup", "ShelvingUnit"], "15": ["Watch", "CounterTop"], "16": ["Spatula", "DiningTable"], "17": ["Mug", "ShelvingUnit"], "18": ["CellPhone", "DiningTable"], "19": ["DishSponge", "GarbageCan"], "20": ["SoapBottle", "GarbageCan"]}, "spawn_objects": [{"objectName": "AlarmClock|surface|6|55", "position": {"x": 6.25, "y": 0.0, "z": 6.75}, "rotation": {"x": -0.0, "y": 0.0, "z": 0.0}}, {"objectName": "AlarmClock|surface|5|35", "position": {"x": 6.75, "y": 0.0, "z": 7.5}, "rotation": {"x": 0.0, "y": 90.0, "z": -0.0}}, {"objectName": "Book|surface|6|51", "position": {"x": 11.25, "y": 0.0, "z": 7.25}, "rotation": {"x": 0.02, "y": 0.0, "z": -0.0}}, {"objectName": "Book|surface|5|36", "position": {"x": 9.25, "y": 0.0, "z": 6.75}, "rotation": {"x": 359.99, "y": -0.0, "z": 0.18}}, {"objectName": "Bowl|surface|4|19", "position": {"x": 8.0, "y": 0.0, "z": 9.25}, "rotation": {"x": 359.87, "y": 269.99, "z": 0.06}}, {"objectName": "Bowl|surface|6|56", "position": {"x": 5.0, "y": 0.0, "z": 9.75}, "rotation": {"x": 359.79, "y": 180.0, "z": 0.02}}, {"objectName": "Bowl|surface|5|29", "position": {"x": 7.25, "y": 0.0, "z": 9.75}, "rotation": {"x": 0.0, "y": 180.0, "z": -0.0}}, {"objectName": "Candle|surface|3|17", "position": {"x": 4.0, "y": 0.0, "z": 4.0}, "rotation": {"x": 357.56, "y": 172.05, "z": 333.27}}, {"objectName": "CD|surface|5|40", "position": {"x": 8.5, "y": 0.0, "z": 11.25}, "rotation": {"x": 0.0, "y": 180.0, "z": -0.0}}], "start_pose": [10.75, 0.9, 7.75], "initial_orientation": 0.0}