{"house_id": 8117, "goals": {"1": ["WineBottle", "GarbageCan"], "2": ["Bowl", "DiningTable"], "3": ["SprayBottle", "DiningTable"], "4": ["Bread", "DiningTable"], "5": ["Vase", "CounterTop"], "6": ["Pan", "DiningTable"], "7": ["Vase", "ShelvingUnit"], "8": ["Spoon", "Mug"], "9": ["Pan", "DiningTable"], "10": ["ButterKnife", "Pan"], "11": ["SprayBottle", "ShelvingUnit"], "12": ["WineBottle", "CounterTop"], "13": ["Mug", "ShelvingUnit"], "14": ["WineBottle", "ShelvingUnit"], "15": ["ButterKnife", "Mug"], "16": ["Spatula", "Pot"], "17": ["Vase", "DiningTable"], "18": ["ButterKnife", "Pot"], "19": ["Spoon", "Pan"], "20": ["WineBottle", "CounterTop"]}, "spawn_objects": [{"objectName": "Apple|surface|2|14", "position": {"x": 3.5, "y": 0.0, "z": 4.75}, "rotation": {"x": 0.0, "y": 270.0, "z": 0.0}}, {"objectName": "Bottle|surface|2|27", "position": {"x": 2.75, "y": 0.0, "z": 4.75}, "rotation": {"x": 359.98, "y": 0.0, "z": 0.0}}, {"objectName": "Bottle|surface|2|26", "position": {"x": 2.75, "y": 0.0, "z": 1.5}, "rotation": {"x": 359.98, "y": 0.0, "z": 0.0}}, {"objectName": "Bowl|surface|2|15", "position": {"x": 4.25, "y": 0.0, "z": 3.25}, "rotation": {"x": 0.0, "y": -0.0, "z": -0.0}}, {"objectName": "Bread|surface|2|2", "position": {"x": 4.5, "y": 0.0, "z": 2.25}, "rotation": {"x": -0.0, "y": -0.0, "z": -0.0}}, {"objectName": "ButterKnife|surface|2|6", "position": {"x": 3.25, "y": 0.0, "z": 2.25}, "rotation": {"x": 0.03, "y": 359.99, "z": 2.24}}, {"objectName": "ButterKnife|surface|2|16", "position": {"x": 6.5, "y": 0.0, "z": 4.75}, "rotation": {"x": 0.03, "y": 269.99, "z": 2.3}}, {"objectName": "ButterKnife|surface|2|7", "position": {"x": 3.75, "y": 0.0, "z": 2.25}, "rotation": {"x": 0.03, "y": 359.99, "z": 2.3}}, {"objectName": "CreditCard|surface|2|1", "position": {"x": 5.5, "y": 0.0, "z": 3.5}, "rotation": {"x": 0.0, "y": 270.0, "z": -0.0}}, {"objectName": "Egg|surface|2|9", "position": {"x": 1.0, "y": 0.0, "z": 4.75}, "rotation": {"x": -0.0, "y": 90.0, "z": -0.0}}, {"objectName": "Egg|surface|2|10", "position": {"x": 4.75, "y": 0.0, "z": 2.5}, "rotation": {"x": -0.0, "y": 90.0, "z": 0.0}}], "start_pose": [2.25, 0.9, 1.75], "initial_orientation": 0.0}