{"house_id": 170, "goals": {"1": ["Watch", "ShelvingUnit"], "2": ["Lettuce", "DiningTable"], "3": ["SoapBottle", "DiningTable"], "4": ["Book", "ArmChair"], "5": ["Watch", "DiningTable"], "6": ["CellPhone", "ShelvingUnit"], "7": ["Statue", "ShelvingUnit"], "8": ["RemoteControl", "ShelvingUnit"], "9": ["CellPhone", "Box"], "10": ["Potato", "Bowl"], "11": ["AlarmClock", "CounterTop"], "12": ["Egg", "DiningTable"], "13": ["Pen", "ShelvingUnit"], "14": ["Apple", "GarbageCan"], "15": ["CD", "DiningTable"], "16": ["CellPhone", "ShelvingUnit"], "17": ["AlarmClock", "DiningTable"], "18": ["Pencil", "Box"], "19": ["CreditCard", "ShelvingUnit"], "20": ["Pillow", "Sofa"]}, "spawn_objects": [{"objectName": "AlarmClock|surface|4|11", "position": {"x": 4.75, "y": 0.0, "z": 6.5}, "rotation": {"x": -0.0, "y": 270.0, "z": 0.0}}, {"objectName": "Apple|surface|6|32", "position": {"x": 1.75, "y": 0.0, "z": 1.75}, "rotation": {"x": -0.0, "y": -0.0, "z": 0.0}}, {"objectName": "Book|surface|7|50", "position": {"x": 2.5, "y": 0.0, "z": 3.25}, "rotation": {"x": 0.03, "y": 0.0, "z": 0.91}}, {"objectName": "Book|surface|7|65", "position": {"x": 9.5, "y": 0.0, "z": 0.5}, "rotation": {"x": 0.0, "y": 90.0, "z": 0.0}}, {"objectName": "Book|surface|7|48", "position": {"x": 7.25, "y": 0.0, "z": 4.0}, "rotation": {"x": 0.0, "y": -0.0, "z": 0.0}}, {"objectName": "Book|surface|4|9", "position": {"x": 6.25, "y": 0.0, "z": 6.0}, "rotation": {"x": 359.99, "y": 180.0, "z": -0.0}}, {"objectName": "Bowl|surface|4|14", "position": {"x": 1.0, "y": 0.0, "z": 2.25}, "rotation": {"x": 0.0, "y": 180.0, "z": -0.0}}, {"objectName": "Bowl|surface|7|51", "position": {"x": 4.5, "y": 0.0, "z": 6.5}, "rotation": {"x": 0.0, "y": 90.0, "z": -0.0}}, {"objectName": "Bread|surface|6|39", "position": {"x": 6.25, "y": 0.0, "z": 7.25}, "rotation": {"x": 0.0, "y": 90.0, "z": 0.0}}, {"objectName": "Candle|surface|5|16", "position": {"x": 6.0, "y": 0.0, "z": 11.0}, "rotation": {"x": 0.07, "y": 0.01, "z": 0.03}}, {"objectName": "Candle|surface|7|52", "position": {"x": 4.0, "y": 0.0, "z": 2.25}, "rotation": {"x": 0.03, "y": 89.99, "z": 359.98}}, {"objectName": "CD|surface|4|1", "position": {"x": 5.5, "y": 0.0, "z": 6.0}, "rotation": {"x": -0.0, "y": -0.0, "z": 0.0}}, {"objectName": "CellPhone|surface|7|60", "position": {"x": 6.0, "y": 0.0, "z": 7.0}, "rotation": {"x": 0.0, "y": 90.0, "z": -0.0}}, {"objectName": "CellPhone|surface|4|8", "position": {"x": 6.5, "y": 0.0, "z": 7.75}, "rotation": {"x": 0.0, "y": 270.0, "z": -0.0}}, {"objectName": "CellPhone|surface|7|55", "position": {"x": 4.75, "y": 0.0, "z": 6.75}, "rotation": {"x": -0.0, "y": 0.0, "z": -0.0}}], "start_pose": [4.25, 0.9, 9.0], "initial_orientation": 0.0}