{"house_id": 840, "goals": {"1": ["ButterKnife", "Bowl"], "2": ["RemoteControl", "ShelvingUnit"], "3": ["CellPhone", "ShelvingUnit"], "4": ["Vase", "CounterTop"], "5": ["Book", "ShelvingUnit"], "6": ["Statue", "DiningTable"], "7": ["Vase", "ShelvingUnit"], "8": ["Book", "Bed"], "9": ["Vase", "CounterTop"], "10": ["Cup", "ShelvingUnit"], "11": ["Pencil", "GarbageCan"], "12": ["Statue", "ShelvingUnit"], "13": ["SoapBottle", "DiningTable"], "14": ["ButterKnife", "CounterTop"], "15": ["Bowl", "ShelvingUnit"], "16": ["Pencil", "DiningTable"], "17": ["Bowl", "CounterTop"], "18": ["Watch", "ShelvingUnit"], "19": ["Bowl", "DiningTable"], "20": ["SoapBottle", "CounterTop"]}, "spawn_objects": [{"objectName": "Book|surface|2|17", "position": {"x": 3.75, "y": 0.0, "z": 4.75}, "rotation": {"x": 0.02, "y": 180.0, "z": 0.91}}, {"objectName": "Book|surface|2|18", "position": {"x": 2.25, "y": 0.0, "z": 6.5}, "rotation": {"x": 359.99, "y": 270.0, "z": 0.11}}, {"objectName": "Bowl|surface|7|12", "position": {"x": 3.25, "y": 0.0, "z": 4.75}, "rotation": {"x": 0.0, "y": -0.0, "z": -0.0}}, {"objectName": "ButterKnife|surface|6|1", "position": {"x": 4.75, "y": 0.0, "z": 2.75}, "rotation": {"x": 0.0, "y": 180.0, "z": 0.09}}, {"objectName": "CellPhone|surface|6|0", "position": {"x": 5.75, "y": 0.0, "z": 2.0}, "rotation": {"x": -0.0, "y": 180.0, "z": -0.0}}], "start_pose": [1.75, 0.9, 3.75], "initial_orientation": 90.0}