{"house_id": 1185, "goals": {"1": ["Bread", "GarbageCan"], "2": ["Fork", "Bowl"], "3": ["Statue", "CounterTop"], "4": ["ButterKnife", "Plate"], "5": ["Bottle", "Sink"], "6": ["AlarmClock", "DiningTable"], "7": ["CellPhone", "CounterTop"], "8": ["Bread", "DiningTable"], "9": ["Pan", "DiningTable"], "10": ["Fork", "Pot"], "11": ["Mug", "CounterTop"], "12": ["Book", "Bed"], "13": ["Newspaper", "Bed"], "14": ["Pencil", "DiningTable"], "15": ["Fork", "Sink"], "16": ["Newspaper", "DiningTable"], "17": ["RemoteControl", "CounterTop"], "18": ["CellPhone", "DiningTable"], "19": ["Bowl", "Sink"], "20": ["Fork", "Pot"]}, "spawn_objects": [{"objectName": "AlarmClock|surface|4|10", "position": {"x": 4.0, "y": 0.0, "z": 4.25}, "rotation": {"x": 359.65, "y": -0.0, "z": -0.0}}, {"objectName": "Apple|surface|6|24", "position": {"x": 4.0, "y": 0.0, "z": 5.5}, "rotation": {"x": 0.0, "y": 270.0, "z": 0.0}}, {"objectName": "Book|surface|6|15", "position": {"x": 9.5, "y": 0.0, "z": 5.5}, "rotation": {"x": 359.99, "y": 90.0, "z": 0.07}}, {"objectName": "Book|surface|7|34", "position": {"x": 8.5, "y": 0.0, "z": 6.0}, "rotation": {"x": -0.0, "y": 270.0, "z": 0.01}}, {"objectName": "Book|surface|4|4", "position": {"x": 4.5, "y": 0.0, "z": 7.0}, "rotation": {"x": 0.03, "y": 270.0, "z": 359.99}}, {"objectName": "Bottle|surface|6|21", "position": {"x": 0.75, "y": 0.0, "z": 7.25}, "rotation": {"x": 359.99, "y": 90.0, "z": 0.0}}, {"objectName": "Bowl|surface|7|35", "position": {"x": 10.75, "y": 0.0, "z": 3.75}, "rotation": {"x": 0.0, "y": -0.0, "z": -0.0}}, {"objectName": "Bowl|surface|4|3", "position": {"x": 3.25, "y": 0.0, "z": 5.5}, "rotation": {"x": 359.99, "y": 0.0, "z": 0.04}}, {"objectName": "Bowl|surface|6|25", "position": {"x": 3.75, "y": 0.0, "z": 3.75}, "rotation": {"x": -0.0, "y": 90.0, "z": 0.0}}, {"objectName": "Bread|surface|6|31", "position": {"x": 4.0, "y": 0.0, "z": 5.75}, "rotation": {"x": -0.0, "y": 180.0, "z": -0.0}}, {"objectName": "ButterKnife|surface|6|32", "position": {"x": 6.25, "y": 0.0, "z": 7.5}, "rotation": {"x": 0.0, "y": 90.0, "z": 0.08}}, {"objectName": "Candle|surface|7|40", "position": {"x": 4.25, "y": 0.0, "z": 4.25}, "rotation": {"x": 0.02, "y": 90.0, "z": 359.98}}, {"objectName": "CellPhone|surface|4|8", "position": {"x": 2.5, "y": 0.0, "z": 4.25}, "rotation": {"x": 0.0, "y": 270.0, "z": -0.0}}, {"objectName": "CreditCard|surface|6|19", "position": {"x": 8.75, "y": 0.0, "z": 2.5}, "rotation": {"x": 0.0, "y": 90.0, "z": -0.0}}, {"objectName": "Cup|surface|6|23", "position": {"x": 3.5, "y": 0.0, "z": 5.25}, "rotation": {"x": 359.96, "y": 180.0, "z": 359.95}}], "start_pose": [6.5, 0.9, 9.25], "initial_orientation": 90.0}