{"house_id": 5286, "goals": {"1": ["Pillow", "ArmChair"], "2": ["Book", "ArmChair"], "3": ["Potato", "DiningTable"], "4": ["CellPhone", "SideTable"], "5": ["Bowl", "Sink"], "6": ["CreditCard", "CounterTop"], "7": ["Newspaper", "CounterTop"], "8": ["CreditCard", "ArmChair"], "9": ["Pencil", "GarbageCan"], "10": ["ButterKnife", "Sink"], "11": ["Mug", "DiningTable"], "12": ["Potato", "Sink"], "13": ["ButterKnife", "Bowl"], "14": ["Watch", "CounterTop"], "15": ["RemoteControl", "SideTable"], "16": ["SprayBottle", "DiningTable"], "17": ["Cup", "DiningTable"], "18": ["Bowl", "SideTable"], "19": ["Vase", "DiningTable"], "20": ["DishSponge", "DiningTable"]}, "spawn_objects": [{"objectName": "AlarmClock|surface|8|89", "position": {"x": 8.0, "y": 0.0, "z": 19.25}, "rotation": {"x": -0.0, "y": 0.0, "z": 0.0}}, {"objectName": "AlarmClock|surface|6|53", "position": {"x": 8.25, "y": 0.0, "z": 15.75}, "rotation": {"x": 0.0, "y": -0.0, "z": -0.0}}, {"objectName": "AlarmClock|surface|7|75", "position": {"x": 0.75, "y": 0.0, "z": 21.0}, "rotation": {"x": 0.0, "y": 0.0, "z": 0.0}}, {"objectName": "Book|surface|4|33", "position": {"x": 7.75, "y": 0.0, "z": 19.0}, "rotation": {"x": 359.98, "y": 180.0, "z": 0.35}}, {"objectName": "Book|surface|6|55", "position": {"x": 8.25, "y": 0.0, "z": 10.25}, "rotation": {"x": 359.99, "y": 180.0, "z": 0.11}}, {"objectName": "Book|surface|4|44", "position": {"x": 0.75, "y": 0.0, "z": 16.25}, "rotation": {"x": 0.02, "y": 270.0, "z": 0.91}}, {"objectName": "Book|surface|3|19", "position": {"x": 11.25, "y": 0.0, "z": 24.5}, "rotation": {"x": -0.0, "y": 270.0, "z": 0.85}}, {"objectName": "Book|surface|6|54", "position": {"x": 10.75, "y": 0.0, "z": 2.75}, "rotation": {"x": 359.99, "y": 180.0, "z": 0.11}}, {"objectName": "Book|surface|7|76", "position": {"x": 8.0, "y": 0.0, "z": 11.5}, "rotation": {"x": 359.99, "y": 180.0, "z": 0.07}}, {"objectName": "Book|surface|8|88", "position": {"x": 8.0, "y": 0.0, "z": 16.75}, "rotation": {"x": -0.0, "y": -0.0, "z": 0.03}}, {"objectName": "Bowl|surface|8|78", "position": {"x": 9.5, "y": 0.0, "z": 23.75}, "rotation": {"x": 0.0, "y": -0.0, "z": -0.0}}], "start_pose": [2.5, 0.9, 10.5], "initial_orientation": 180.0}