{"house_id": 3126, "goals": {"1": ["SoapBottle", "GarbageCan"], "2": ["Egg", "DiningTable"], "3": ["Knife", "Mug"], "4": ["Vase", "DiningTable"], "5": ["Mug", "CounterTop"], "6": ["ButterKnife", "DiningTable"], "7": ["Pillow", "Sofa"], "8": ["Watch", "ShelvingUnit"], "9": ["Egg", "Sink"], "10": ["Vase", "ShelvingUnit"], "11": ["CellPhone", "Sofa"], "12": ["Lettuce", "GarbageCan"], "13": ["Egg", "Bowl"], "14": ["Book", "CounterTop"], "15": ["CellPhone", "CounterTop"], "16": ["Mug", "DiningTable"], "17": ["Bread", "DiningTable"], "18": ["AlarmClock", "CounterTop"], "19": ["CellPhone", "Bed"], "20": ["RemoteControl", "ShelvingUnit"]}, "spawn_objects": [{"objectName": "AlarmClock|surface|4|4", "position": {"x": 5.75, "y": 0.0, "z": 0.25}, "rotation": {"x": 0.11, "y": 269.99, "z": 0.12}}, {"objectName": "Apple|surface|6|17", "position": {"x": 6.5, "y": 0.0, "z": 8.25}, "rotation": {"x": 0.0, "y": 180.0, "z": -0.0}}, {"objectName": "Book|surface|4|8", "position": {"x": 5.25, "y": 0.0, "z": 2.75}, "rotation": {"x": 359.99, "y": 180.0, "z": 0.12}}, {"objectName": "Book|surface|7|34", "position": {"x": 7.0, "y": 0.0, "z": 8.75}, "rotation": {"x": 0.0, "y": -0.0, "z": 0.26}}, {"objectName": "Book|surface|4|6", "position": {"x": 7.0, "y": 0.0, "z": 3.25}, "rotation": {"x": 0.02, "y": 270.0, "z": 0.01}}, {"objectName": "Bowl|surface|7|32", "position": {"x": 6.75, "y": 0.0, "z": 7.25}, "rotation": {"x": -0.0, "y": -0.0, "z": -0.0}}, {"objectName": "Bread|surface|6|15", "position": {"x": 1.0, "y": 0.0, "z": 4.5}, "rotation": {"x": -0.0, "y": 180.0, "z": -0.0}}, {"objectName": "ButterKnife|surface|6|20", "position": {"x": 3.5, "y": 0.0, "z": 5.75}, "rotation": {"x": 0.0, "y": 180.0, "z": 0.08}}], "start_pose": [2.75, 0.9, 6.75], "initial_orientation": 0.0}